<?xml version="1.0"?>
<opencv_storage>
<stage64>
  <maxWeakCount>94</maxWeakCount>
  <stageThreshold>-4.6652811765670776e-01</stageThreshold>
  <weakClassifiers>
    <_>
      <internalNodes>
        0 -1 143834 -7.0430780760943890e-04</internalNodes>
      <leafValues>
        5.5199998617172241e-01 2.6044443249702454e-01</leafValues></_>
    <_>
      <internalNodes>
        0 -1 10127 -1.2277638912200928e-01</internalNodes>
      <leafValues>
        -1.2710873037576675e-02 6.1289763450622559e-01</leafValues></_>
    <_>
      <internalNodes>
        0 -1 10695 -1.3019415736198425e-01</internalNodes>
      <leafValues>
        2.1209608763456345e-02 -7.4472051858901978e-01</leafValues></_>
    <_>
      <internalNodes>
        0 -1 20838 -3.2987231016159058e-01</internalNodes>
      <leafValues>
        -2.9317002743482590e-02 4.6595716476440430e-01</leafValues></_>
    <_>
      <internalNodes>
        0 -1 87565 -4.6422414481639862e-02</internalNodes>
      <leafValues>
        4.7281306236982346e-02 -4.0619164705276489e-01</leafValues></_>
    <_>
      <internalNodes>
        0 -1 104416 -2.9038896784186363e-02</internalNodes>
      <leafValues>
        -1.3095336034893990e-02 5.0514698028564453e-01</leafValues></_>
    <_>
      <internalNodes>
        0 -1 90393 -1.7991092056035995e-02</internalNodes>
      <leafValues>
        3.4426981583237648e-03 -8.4282243251800537e-01</leafValues></_>
    <_>
      <internalNodes>
        0 -1 98654 -1.6017248854041100e-03</internalNodes>
      <leafValues>
        -9.9824611097574234e-03 8.1976258754730225e-01</leafValues></_>
    <_>
      <internalNodes>
        0 -1 119069 2.6559381512925029e-04</internalNodes>
      <leafValues>
        1.2417192012071609e-01 -1.8979789316654205e-01</leafValues></_>
    <_>
      <internalNodes>
        0 -1 25856 -5.4652662947773933e-03</internalNodes>
      <leafValues>
        5.6289428472518921e-01 -2.0170040428638458e-02</leafValues></_>
    <_>
      <internalNodes>
        0 -1 26863 4.8804050311446190e-03</internalNodes>
      <leafValues>
        -1.3806533813476563e-01 1.9015398621559143e-01</leafValues></_>
    <_>
      <internalNodes>
        0 -1 128746 -1.0116253048181534e-02</internalNodes>
      <leafValues>
        5.3574579954147339e-01 -3.9197508245706558e-02</leafValues></_>
    <_>
      <internalNodes>
        0 -1 161381 -3.4031312679871917e-04</internalNodes>
      <leafValues>
        -2.1577699482440948e-01 1.1828988045454025e-01</leafValues></_>
    <_>
      <internalNodes>
        0 -1 98541 -4.9198716878890991e-03</internalNodes>
      <leafValues>
        -4.0101480484008789e-01 3.3481501042842865e-02</leafValues></_>
    <_>
      <internalNodes>
        0 -1 123705 -2.5580562651157379e-02</internalNodes>
      <leafValues>
        -2.8540664911270142e-01 7.0332452654838562e-02</leafValues></_>
    <_>
      <internalNodes>
        0 -1 40118 -2.3410876747220755e-03</internalNodes>
      <leafValues>
        -1.5415492653846741e-01 1.2604536116123199e-01</leafValues></_>
    <_>
      <internalNodes>
        0 -1 91227 8.1790547119453549e-04</internalNodes>
      <leafValues>
        -4.7428280115127563e-02 4.5211020112037659e-01</leafValues></_>
    <_>
      <internalNodes>
        0 -1 14417 1.8449332565069199e-03</internalNodes>
      <leafValues>
        -2.8796851634979248e-02 7.3797696828842163e-01</leafValues></_>
    <_>
      <internalNodes>
        0 -1 69601 1.6687754541635513e-02</internalNodes>
      <leafValues>
        5.2938036620616913e-02 -3.8399890065193176e-01</leafValues></_>
    <_>
      <internalNodes>
        0 -1 48587 -1.3127347454428673e-02</internalNodes>
      <leafValues>
        -2.3634830117225647e-01 9.7217239439487457e-02</leafValues></_>
    <_>
      <internalNodes>
        0 -1 80621 1.4165836619213223e-03</internalNodes>
      <leafValues>
        1.4106461405754089e-01 -1.4930316805839539e-01</leafValues></_>
    <_>
      <internalNodes>
        0 -1 70555 -5.7515152730047703e-04</internalNodes>
      <leafValues>
        3.6211577057838440e-01 -5.5897958576679230e-02</leafValues></_>
    <_>
      <internalNodes>
        0 -1 49640 5.4580029100179672e-03</internalNodes>
      <leafValues>
        3.1121850013732910e-02 -6.6334664821624756e-01</leafValues></_>
    <_>
      <internalNodes>
        0 -1 98402 -3.7377702537924051e-03</internalNodes>
      <leafValues>
        9.6015036106109619e-01 -2.4147903546690941e-02</leafValues></_>
    <_>
      <internalNodes>
        0 -1 60440 -1.0005924850702286e-03</internalNodes>
      <leafValues>
        -5.4483264684677124e-01 4.0669653564691544e-02</leafValues></_>
    <_>
      <internalNodes>
        0 -1 126640 7.2220358997583389e-03</internalNodes>
      <leafValues>
        -3.9979040622711182e-02 5.1245999336242676e-01</leafValues></_>
    <_>
      <internalNodes>
        0 -1 13486 1.1051376350224018e-02</internalNodes>
      <leafValues>
        -2.8210924938321114e-02 6.4856588840484619e-01</leafValues></_>
    <_>
      <internalNodes>
        0 -1 80642 -2.6785783469676971e-02</internalNodes>
      <leafValues>
        -1.7643647268414497e-02 8.9556956291198730e-01</leafValues></_>
    <_>
      <internalNodes>
        0 -1 159585 -1.8808357417583466e-03</internalNodes>
      <leafValues>
        2.8516843914985657e-01 -5.8014478534460068e-02</leafValues></_>
    <_>
      <internalNodes>
        0 -1 147098 1.4000792987644672e-02</internalNodes>
      <leafValues>
        3.1212791800498962e-02 -6.5445101261138916e-01</leafValues></_>
    <_>
      <internalNodes>
        0 -1 122762 3.2002553343772888e-02</internalNodes>
      <leafValues>
        -2.9163505882024765e-02 7.4416583776473999e-01</leafValues></_>
    <_>
      <internalNodes>
        0 -1 121687 1.0637394152581692e-02</internalNodes>
      <leafValues>
        1.0181828588247299e-01 -2.2783546149730682e-01</leafValues></_>
    <_>
      <internalNodes>
        0 -1 135635 9.7876163199543953e-03</internalNodes>
      <leafValues>
        -6.6667854785919189e-02 3.2169657945632935e-01</leafValues></_>
    <_>
      <internalNodes>
        0 -1 139503 5.6981265544891357e-02</internalNodes>
      <leafValues>
        3.6548342555761337e-02 -5.8373850584030151e-01</leafValues></_>
    <_>
      <internalNodes>
        0 -1 64282 5.2451631054282188e-03</internalNodes>
      <leafValues>
        3.7793789058923721e-02 -5.5123734474182129e-01</leafValues></_>
    <_>
      <internalNodes>
        0 -1 75715 -3.9838551310822368e-04</internalNodes>
      <leafValues>
        3.2106170058250427e-01 -6.6500626504421234e-02</leafValues></_>
    <_>
      <internalNodes>
        0 -1 2324 9.1505639255046844e-02</internalNodes>
      <leafValues>
        -2.0311418920755386e-02 8.9255928993225098e-01</leafValues></_>
    <_>
      <internalNodes>
        0 -1 124302 -4.3350935447961092e-04</internalNodes>
      <leafValues>
        1.5718364715576172e-01 -1.1648334562778473e-01</leafValues></_>
    <_>
      <internalNodes>
        0 -1 108215 4.0890211239457130e-03</internalNodes>
      <leafValues>
        -1.1632543057203293e-01 1.7650978267192841e-01</leafValues></_>
    <_>
      <internalNodes>
        0 -1 79719 -2.2854194045066833e-02</internalNodes>
      <leafValues>
        1.7770631611347198e-01 -1.0561064630746841e-01</leafValues></_>
    <_>
      <internalNodes>
        0 -1 80325 -7.9392985207960010e-04</internalNodes>
      <leafValues>
        -1.5876662731170654e-01 1.9865195453166962e-01</leafValues></_>
    <_>
      <internalNodes>
        0 -1 47047 1.0647200979292393e-03</internalNodes>
      <leafValues>
        4.6053525060415268e-02 -4.3850755691528320e-01</leafValues></_>
    <_>
      <internalNodes>
        0 -1 156284 1.1945555452257395e-03</internalNodes>
      <leafValues>
        9.3186967074871063e-02 -2.0382623374462128e-01</leafValues></_>
    <_>
      <internalNodes>
        0 -1 150140 -2.1915121469646692e-03</internalNodes>
      <leafValues>
        5.9921640157699585e-01 -3.5970751196146011e-02</leafValues></_>
    <_>
      <internalNodes>
        0 -1 144054 -1.1276725679636002e-02</internalNodes>
      <leafValues>
        4.4680580496788025e-02 -5.3907632827758789e-01</leafValues></_>
    <_>
      <internalNodes>
        0 -1 3161 1.1873388430103660e-03</internalNodes>
      <leafValues>
        1.2257102876901627e-01 -1.5778797864913940e-01</leafValues></_>
    <_>
      <internalNodes>
        0 -1 69906 -2.4276621639728546e-02</internalNodes>
      <leafValues>
        -4.6517187356948853e-01 5.0956003367900848e-02</leafValues></_>
    <_>
      <internalNodes>
        0 -1 138479 1.0969189926981926e-02</internalNodes>
      <leafValues>
        -2.2804457694292068e-02 1.</leafValues></_>
    <_>
      <internalNodes>
        0 -1 96441 3.9305957034230232e-03</internalNodes>
      <leafValues>
        -3.5937950015068054e-02 4.5503291487693787e-01</leafValues></_>
    <_>
      <internalNodes>
        0 -1 158559 -5.9188355226069689e-04</internalNodes>
      <leafValues>
        1.1599579453468323e-01 -1.7803944647312164e-01</leafValues></_>
    <_>
      <internalNodes>
        0 -1 150770 -5.6505575776100159e-02</internalNodes>
      <leafValues>
        -6.5223920345306396e-01 3.3109419047832489e-02</leafValues></_>
    <_>
      <internalNodes>
        0 -1 104457 -1.7613524571061134e-02</internalNodes>
      <leafValues>
        -2.6521807909011841e-01 6.8113721907138824e-02</leafValues></_>
    <_>
      <internalNodes>
        0 -1 119680 1.4956402592360973e-03</internalNodes>
      <leafValues>
        1.1962275207042694e-01 -1.7666204273700714e-01</leafValues></_>
    <_>
      <internalNodes>
        0 -1 126771 -1.2561501935124397e-02</internalNodes>
      <leafValues>
        4.5826178789138794e-01 -5.2178923040628433e-02</leafValues></_>
    <_>
      <internalNodes>
        0 -1 157057 -2.6446897536516190e-02</internalNodes>
      <leafValues>
        -7.9055160284042358e-01 4.2127612978219986e-02</leafValues></_>
    <_>
      <internalNodes>
        0 -1 147629 -3.1288377940654755e-02</internalNodes>
      <leafValues>
        4.9583786725997925e-01 -4.7378141433000565e-02</leafValues></_>
    <_>
      <internalNodes>
        0 -1 109224 1.7309144139289856e-02</internalNodes>
      <leafValues>
        6.0871824622154236e-02 -3.4762713313102722e-01</leafValues></_>
    <_>
      <internalNodes>
        0 -1 114159 3.1638364307582378e-03</internalNodes>
      <leafValues>
        -7.3842629790306091e-02 2.8746694326400757e-01</leafValues></_>
    <_>
      <internalNodes>
        0 -1 95770 -3.7225856794975698e-04</internalNodes>
      <leafValues>
        -2.0970113575458527e-01 1.0525006800889969e-01</leafValues></_>
    <_>
      <internalNodes>
        0 -1 113250 -3.2036647200584412e-02</internalNodes>
      <leafValues>
        8.8841271400451660e-01 -2.2502172738313675e-02</leafValues></_>
    <_>
      <internalNodes>
        0 -1 23623 7.4292742647230625e-04</internalNodes>
      <leafValues>
        -4.0707226842641830e-02 4.4026905298233032e-01</leafValues></_>
    <_>
      <internalNodes>
        0 -1 152458 -8.9541766792535782e-03</internalNodes>
      <leafValues>
        -5.1882499456405640e-01 4.4315859675407410e-02</leafValues></_>
    <_>
      <internalNodes>
        0 -1 68957 -1.0753109119832516e-02</internalNodes>
      <leafValues>
        4.0019139647483826e-01 -4.5425947755575180e-02</leafValues></_>
    <_>
      <internalNodes>
        0 -1 154916 5.8330884203314781e-03</internalNodes>
      <leafValues>
        1.0496871173381805e-01 -2.0176368951797485e-01</leafValues></_>
    <_>
      <internalNodes>
        0 -1 145500 -5.1861856132745743e-02</internalNodes>
      <leafValues>
        5.7894283533096313e-01 -3.2532341778278351e-02</leafValues></_>
    <_>
      <internalNodes>
        0 -1 28662 5.4344758391380310e-03</internalNodes>
      <leafValues>
        -2.1996539086103439e-02 8.2587188482284546e-01</leafValues></_>
    <_>
      <internalNodes>
        0 -1 72551 4.4554822146892548e-02</internalNodes>
      <leafValues>
        -3.1537771224975586e-02 5.3478461503982544e-01</leafValues></_>
    <_>
      <internalNodes>
        0 -1 20090 -2.1845650672912598e-01</internalNodes>
      <leafValues>
        8.0972111225128174e-01 -2.0038601011037827e-02</leafValues></_>
    <_>
      <internalNodes>
        0 -1 11667 -1.1147825047373772e-02</internalNodes>
      <leafValues>
        -2.3925928771495819e-01 8.6985029280185699e-02</leafValues></_>
    <_>
      <internalNodes>
        0 -1 70608 9.1761201620101929e-03</internalNodes>
      <leafValues>
        -3.6991871893405914e-02 5.5406928062438965e-01</leafValues></_>
    <_>
      <internalNodes>
        0 -1 80047 5.1683090627193451e-02</internalNodes>
      <leafValues>
        4.9707625061273575e-02 -4.6472483873367310e-01</leafValues></_>
    <_>
      <internalNodes>
        0 -1 81513 2.0060301758348942e-03</internalNodes>
      <leafValues>
        5.0477292388677597e-02 -3.8352748751640320e-01</leafValues></_>
    <_>
      <internalNodes>
        0 -1 27774 -3.7355857784859836e-04</internalNodes>
      <leafValues>
        2.5860828161239624e-01 -8.1171408295631409e-02</leafValues></_>
    <_>
      <internalNodes>
        0 -1 62129 6.5238168463110924e-03</internalNodes>
      <leafValues>
        -8.2485266029834747e-02 2.5088021159172058e-01</leafValues></_>
    <_>
      <internalNodes>
        0 -1 37133 -1.2017713487148285e-01</internalNodes>
      <leafValues>
        6.5325194597244263e-01 -3.2503705471754074e-02</leafValues></_>
    <_>
      <internalNodes>
        0 -1 66693 2.7794330380856991e-03</internalNodes>
      <leafValues>
        6.4968630671501160e-02 -3.2179743051528931e-01</leafValues></_>
    <_>
      <internalNodes>
        0 -1 43817 7.9881753772497177e-03</internalNodes>
      <leafValues>
        -4.7102849930524826e-02 4.6227908134460449e-01</leafValues></_>
    <_>
      <internalNodes>
        0 -1 30890 -3.1937921047210693e-01</internalNodes>
      <leafValues>
        1. -1.6910856589674950e-02</leafValues></_>
    <_>
      <internalNodes>
        0 -1 85334 3.1955749727785587e-03</internalNodes>
      <leafValues>
        -4.9810923635959625e-02 3.4647497534751892e-01</leafValues></_>
    <_>
      <internalNodes>
        0 -1 135058 -4.2906990274786949e-03</internalNodes>
      <leafValues>
        -4.3538829684257507e-01 4.4455081224441528e-02</leafValues></_>
    <_>
      <internalNodes>
        0 -1 50606 4.0246369317173958e-03</internalNodes>
      <leafValues>
        -4.8974629491567612e-02 3.9265376329421997e-01</leafValues></_>
    <_>
      <internalNodes>
        0 -1 71700 1.7732450738549232e-02</internalNodes>
      <leafValues>
        3.3213686197996140e-02 -6.7314106225967407e-01</leafValues></_>
    <_>
      <internalNodes>
        0 -1 155121 2.5245055439881980e-04</internalNodes>
      <leafValues>
        -1.5410950779914856e-01 1.3164681196212769e-01</leafValues></_>
    <_>
      <internalNodes>
        0 -1 34430 6.8959651980549097e-04</internalNodes>
      <leafValues>
        8.2661621272563934e-02 -2.5299036502838135e-01</leafValues></_>
    <_>
      <internalNodes>
        0 -1 123969 3.4877602010965347e-03</internalNodes>
      <leafValues>
        -7.5279027223587036e-02 2.9466456174850464e-01</leafValues></_>
    <_>
      <internalNodes>
        0 -1 157353 -4.2858514934778214e-03</internalNodes>
      <leafValues>
        -3.0201154947280884e-01 6.4873993396759033e-02</leafValues></_>
    <_>
      <internalNodes>
        0 -1 132009 -8.3056569099426270e-02</internalNodes>
      <leafValues>
        -3.5860948264598846e-02 5.6771719455718994e-01</leafValues></_>
    <_>
      <internalNodes>
        0 -1 149653 -1.5887241810560226e-02</internalNodes>
      <leafValues>
        5.8225627988576889e-02 -5.0773036479949951e-01</leafValues></_>
    <_>
      <internalNodes>
        0 -1 37338 -1.1655755341053009e-02</internalNodes>
      <leafValues>
        -6.0239171981811523e-01 3.0861476436257362e-02</leafValues></_>
    <_>
      <internalNodes>
        0 -1 84330 6.6513475030660629e-03</internalNodes>
      <leafValues>
        -7.6995700597763062e-02 3.0132400989532471e-01</leafValues></_>
    <_>
      <internalNodes>
        0 -1 10019 -1.5230649150907993e-03</internalNodes>
      <leafValues>
        -1.8875265121459961e-01 1.1218950152397156e-01</leafValues></_>
    <_>
      <internalNodes>
        0 -1 156549 -2.9872948653064668e-04</internalNodes>
      <leafValues>
        -1.3544006645679474e-01 1.5488649904727936e-01</leafValues></_>
    <_>
      <internalNodes>
        0 -1 155272 -1.2510931119322777e-03</internalNodes>
      <leafValues>
        1.6443186998367310e-01 -1.3255435228347778e-01</leafValues></_>
    <_>
      <internalNodes>
        0 -1 149997 6.6961580887436867e-03</internalNodes>
      <leafValues>
        8.8893435895442963e-02 -2.5552123785018921e-01</leafValues></_></weakClassifiers></stage64>
</opencv_storage>
