<?xml version="1.0"?>
<opencv_storage>
<stage7>
  <maxWeakCount>43</maxWeakCount>
  <stageThreshold>-1.0584566593170166e+00</stageThreshold>
  <weakClassifiers>
    <_>
      <internalNodes>
        0 -1 157628 -1.0523444414138794e-01</internalNodes>
      <leafValues>
        -6.9892472028732300e-01 2.7045768499374390e-01</leafValues></_>
    <_>
      <internalNodes>
        0 -1 144638 -3.1886346638202667e-02</internalNodes>
      <leafValues>
        2.5920450687408447e-01 -4.3007284402847290e-01</leafValues></_>
    <_>
      <internalNodes>
        0 -1 5220 3.5684637725353241e-02</internalNodes>
      <leafValues>
        -2.7041825652122498e-01 2.9660534858703613e-01</leafValues></_>
    <_>
      <internalNodes>
        0 -1 5890 1.2027813121676445e-02</internalNodes>
      <leafValues>
        -8.2873523235321045e-02 6.1487770080566406e-01</leafValues></_>
    <_>
      <internalNodes>
        0 -1 160765 -1.1934745125472546e-03</internalNodes>
      <leafValues>
        5.9516334533691406e-01 -9.2205017805099487e-02</leafValues></_>
    <_>
      <internalNodes>
        0 -1 886 4.8944847658276558e-03</internalNodes>
      <leafValues>
        -3.1398659944534302e-01 1.8692737817764282e-01</leafValues></_>
    <_>
      <internalNodes>
        0 -1 154788 1.6451599076390266e-03</internalNodes>
      <leafValues>
        -9.6578314900398254e-02 6.0423374176025391e-01</leafValues></_>
    <_>
      <internalNodes>
        0 -1 84713 1.2123243323003408e-05</internalNodes>
      <leafValues>
        -1.7738759517669678e-01 2.6609900593757629e-01</leafValues></_>
    <_>
      <internalNodes>
        0 -1 121237 1.8998765153810382e-04</internalNodes>
      <leafValues>
        -1.2027101963758469e-01 3.4991139173507690e-01</leafValues></_>
    <_>
      <internalNodes>
        0 -1 157502 -6.5904250368475914e-04</internalNodes>
      <leafValues>
        6.0635149478912354e-01 -8.0990567803382874e-02</leafValues></_>
    <_>
      <internalNodes>
        0 -1 49472 -2.2000262141227722e-01</internalNodes>
      <leafValues>
        -8.0761796236038208e-01 6.3575878739356995e-02</leafValues></_>
    <_>
      <internalNodes>
        0 -1 114361 -3.2181155984289944e-04</internalNodes>
      <leafValues>
        4.0279144048690796e-01 -1.3938944041728973e-01</leafValues></_>
    <_>
      <internalNodes>
        0 -1 8827 4.1580665856599808e-03</internalNodes>
      <leafValues>
        -5.8099098503589630e-02 6.9994240999221802e-01</leafValues></_>
    <_>
      <internalNodes>
        0 -1 9910 3.5498023033142090e-02</internalNodes>
      <leafValues>
        7.8007809817790985e-02 -6.4130359888076782e-01</leafValues></_>
    <_>
      <internalNodes>
        0 -1 48355 -2.1830203011631966e-02</internalNodes>
      <leafValues>
        3.3374625444412231e-01 -1.5761992335319519e-01</leafValues></_>
    <_>
      <internalNodes>
        0 -1 7086 1.4325946569442749e-01</internalNodes>
      <leafValues>
        -1.5204747021198273e-01 4.1185075044631958e-01</leafValues></_>
    <_>
      <internalNodes>
        0 -1 127030 4.2969517409801483e-02</internalNodes>
      <leafValues>
        -6.6375508904457092e-02 6.0683584213256836e-01</leafValues></_>
    <_>
      <internalNodes>
        0 -1 38561 6.9041103124618530e-02</internalNodes>
      <leafValues>
        -1.5464253723621368e-01 3.0250599980354309e-01</leafValues></_>
    <_>
      <internalNodes>
        0 -1 46621 3.9811371825635433e-03</internalNodes>
      <leafValues>
        -8.0319918692111969e-02 6.0984551906585693e-01</leafValues></_>
    <_>
      <internalNodes>
        0 -1 10012 5.4185278713703156e-04</internalNodes>
      <leafValues>
        -8.0042533576488495e-02 5.1436948776245117e-01</leafValues></_>
    <_>
      <internalNodes>
        0 -1 89818 -1.5486314892768860e-02</internalNodes>
      <leafValues>
        -7.5825594365596771e-02 5.8800429105758667e-01</leafValues></_>
    <_>
      <internalNodes>
        0 -1 99951 1.3496683095581830e-04</internalNodes>
      <leafValues>
        -1.2747253477573395e-01 3.0706450343132019e-01</leafValues></_>
    <_>
      <internalNodes>
        0 -1 13193 -1.3475206494331360e-01</internalNodes>
      <leafValues>
        -5.6364220380783081e-01 8.5301250219345093e-02</leafValues></_>
    <_>
      <internalNodes>
        0 -1 95454 -1.4096829108893871e-02</internalNodes>
      <leafValues>
        -2.4047954380512238e-01 1.8763835728168488e-01</leafValues></_>
    <_>
      <internalNodes>
        0 -1 50384 1.5368312233476900e-05</internalNodes>
      <leafValues>
        -1.8028421700000763e-01 2.8286665678024292e-01</leafValues></_>
    <_>
      <internalNodes>
        0 -1 44561 -5.0515187904238701e-03</internalNodes>
      <leafValues>
        -3.6496627330780029e-01 1.3044495880603790e-01</leafValues></_>
    <_>
      <internalNodes>
        0 -1 84833 2.2173097822815180e-03</internalNodes>
      <leafValues>
        -9.4995543360710144e-02 5.2606755495071411e-01</leafValues></_>
    <_>
      <internalNodes>
        0 -1 107832 -2.2401884198188782e-02</internalNodes>
      <leafValues>
        7.7060747146606445e-01 -5.2172925323247910e-02</leafValues></_>
    <_>
      <internalNodes>
        0 -1 28532 -8.4761008620262146e-02</internalNodes>
      <leafValues>
        -7.8911352157592773e-01 7.1338944137096405e-02</leafValues></_>
    <_>
      <internalNodes>
        0 -1 2132 -3.7028461520094424e-05</internalNodes>
      <leafValues>
        2.9452911019325256e-01 -1.7031566798686981e-01</leafValues></_>
    <_>
      <internalNodes>
        0 -1 158752 -3.5015374422073364e-02</internalNodes>
      <leafValues>
        5.1833176612854004e-01 -8.4844261407852173e-02</leafValues></_>
    <_>
      <internalNodes>
        0 -1 60775 3.6024264991283417e-02</internalNodes>
      <leafValues>
        8.7556675076484680e-02 -6.2856411933898926e-01</leafValues></_>
    <_>
      <internalNodes>
        0 -1 156992 -4.9258578568696976e-02</internalNodes>
      <leafValues>
        -7.0052379369735718e-01 6.3686214387416840e-02</leafValues></_>
    <_>
      <internalNodes>
        0 -1 161745 5.5261095985770226e-04</internalNodes>
      <leafValues>
        -8.9929841458797455e-02 5.7276892662048340e-01</leafValues></_>
    <_>
      <internalNodes>
        0 -1 20939 1.6234898794209585e-05</internalNodes>
      <leafValues>
        -1.6794614493846893e-01 2.6530691981315613e-01</leafValues></_>
    <_>
      <internalNodes>
        0 -1 33252 9.9237426184117794e-04</internalNodes>
      <leafValues>
        1.0105630755424500e-01 -4.1950613260269165e-01</leafValues></_>
    <_>
      <internalNodes>
        0 -1 1795 -1.4958450198173523e-01</internalNodes>
      <leafValues>
        4.5272982120513916e-01 -1.0803843289613724e-01</leafValues></_>
    <_>
      <internalNodes>
        0 -1 155089 1.7474934793426655e-05</internalNodes>
      <leafValues>
        -1.9219379127025604e-01 2.5320771336555481e-01</leafValues></_>
    <_>
      <internalNodes>
        0 -1 114080 -4.6261024544946849e-04</internalNodes>
      <leafValues>
        -3.0334666371345520e-01 1.5223042666912079e-01</leafValues></_>
    <_>
      <internalNodes>
        0 -1 143194 -1.8646717071533203e-02</internalNodes>
      <leafValues>
        -4.1637060046195984e-01 9.7033224999904633e-02</leafValues></_>
    <_>
      <internalNodes>
        0 -1 157401 7.0576171856373549e-04</internalNodes>
      <leafValues>
        -6.1300672590732574e-02 7.1153336763381958e-01</leafValues></_>
    <_>
      <internalNodes>
        0 -1 65011 4.2821499519050121e-03</internalNodes>
      <leafValues>
        -1.6112881898880005e-01 2.8465065360069275e-01</leafValues></_>
    <_>
      <internalNodes>
        0 -1 70740 3.4984655212610960e-03</internalNodes>
      <leafValues>
        -8.7568745017051697e-02 5.9464335441589355e-01</leafValues></_></weakClassifiers></stage7>
</opencv_storage>
