<?xml version="1.0"?>
<opencv_storage>
<stage13>
  <maxWeakCount>28</maxWeakCount>
  <stageThreshold>-5.7480514049530029e-01</stageThreshold>
  <weakClassifiers>
    <_>
      <internalNodes>
        0 -1 13304 -4.3718167580664158e-03</internalNodes>
      <leafValues>
        -3.2716050744056702e-01 6.1538463830947876e-01</leafValues></_>
    <_>
      <internalNodes>
        0 -1 78754 -8.1578865647315979e-02</internalNodes>
      <leafValues>
        1.2030880153179169e-01 -4.9677354097366333e-01</leafValues></_>
    <_>
      <internalNodes>
        0 -1 147128 -3.4702874720096588e-02</internalNodes>
      <leafValues>
        -2.9314625263214111e-01 2.2515361011028290e-01</leafValues></_>
    <_>
      <internalNodes>
        0 -1 139651 -7.0313643664121628e-04</internalNodes>
      <leafValues>
        -3.4195527434349060e-01 1.8159864842891693e-01</leafValues></_>
    <_>
      <internalNodes>
        0 -1 133594 7.1704550646245480e-04</internalNodes>
      <leafValues>
        1.4252974092960358e-01 -6.5468102693557739e-01</leafValues></_>
    <_>
      <internalNodes>
        0 -1 162144 4.3078036978840828e-03</internalNodes>
      <leafValues>
        1.4110651612281799e-01 -4.5135453343391418e-01</leafValues></_>
    <_>
      <internalNodes>
        0 -1 159521 3.9643887430429459e-04</internalNodes>
      <leafValues>
        1.8879778683185577e-01 -3.6254313588142395e-01</leafValues></_>
    <_>
      <internalNodes>
        0 -1 41554 -3.4894882701337337e-03</internalNodes>
      <leafValues>
        6.8454265594482422e-01 -1.0535419732332230e-01</leafValues></_>
    <_>
      <internalNodes>
        0 -1 26822 2.8057831805199385e-03</internalNodes>
      <leafValues>
        1.0887905955314636e-01 -7.4687504768371582e-01</leafValues></_>
    <_>
      <internalNodes>
        0 -1 63141 -3.0884992331266403e-02</internalNodes>
      <leafValues>
        5.1486110687255859e-01 -1.5516775846481323e-01</leafValues></_>
    <_>
      <internalNodes>
        0 -1 52536 -1.1182487010955811e-01</internalNodes>
      <leafValues>
        5.5325889587402344e-01 -1.2186439335346222e-01</leafValues></_>
    <_>
      <internalNodes>
        0 -1 103266 1.8955350387841463e-03</internalNodes>
      <leafValues>
        -2.0145310461521149e-01 3.9215019345283508e-01</leafValues></_>
    <_>
      <internalNodes>
        0 -1 89985 9.1041089035570621e-04</internalNodes>
      <leafValues>
        2.3299609124660492e-01 -3.3381414413452148e-01</leafValues></_>
    <_>
      <internalNodes>
        0 -1 28404 2.2725979797542095e-03</internalNodes>
      <leafValues>
        -3.3032566308975220e-01 2.1872946619987488e-01</leafValues></_>
    <_>
      <internalNodes>
        0 -1 57223 2.9351944103837013e-03</internalNodes>
      <leafValues>
        -1.1351897567510605e-01 6.4452236890792847e-01</leafValues></_>
    <_>
      <internalNodes>
        0 -1 70782 4.0033806726569310e-05</internalNodes>
      <leafValues>
        -3.7999066710472107e-01 2.2120517492294312e-01</leafValues></_>
    <_>
      <internalNodes>
        0 -1 6328 1.3080221414566040e-01</internalNodes>
      <leafValues>
        1.0614383965730667e-01 -6.8098872900009155e-01</leafValues></_>
    <_>
      <internalNodes>
        0 -1 9950 2.8027694672346115e-02</internalNodes>
      <leafValues>
        1.0774250328540802e-01 -6.2027472257614136e-01</leafValues></_>
    <_>
      <internalNodes>
        0 -1 30969 1.8111953139305115e-01</internalNodes>
      <leafValues>
        -1.2488754838705063e-01 6.9356590509414673e-01</leafValues></_>
    <_>
      <internalNodes>
        0 -1 2352 4.7912229783833027e-03</internalNodes>
      <leafValues>
        -2.3071664571762085e-01 2.9898387193679810e-01</leafValues></_>
    <_>
      <internalNodes>
        0 -1 68564 2.6505524292588234e-03</internalNodes>
      <leafValues>
        1.5973056852817535e-01 -4.4420951604843140e-01</leafValues></_>
    <_>
      <internalNodes>
        0 -1 59607 -7.3753250762820244e-03</internalNodes>
      <leafValues>
        5.3911232948303223e-01 -1.6394065320491791e-01</leafValues></_>
    <_>
      <internalNodes>
        0 -1 158950 -2.7835923247039318e-03</internalNodes>
      <leafValues>
        -5.2418136596679688e-01 1.7826931178569794e-01</leafValues></_>
    <_>
      <internalNodes>
        0 -1 156493 -1.2711171992123127e-02</internalNodes>
      <leafValues>
        3.9027848839759827e-01 -2.3408076167106628e-01</leafValues></_>
    <_>
      <internalNodes>
        0 -1 146396 -2.1114113042131066e-04</internalNodes>
      <leafValues>
        -3.6141225695610046e-01 2.4655342102050781e-01</leafValues></_>
    <_>
      <internalNodes>
        0 -1 48932 -1.0760426521301270e-02</internalNodes>
      <leafValues>
        -8.8890135288238525e-01 1.0156243294477463e-01</leafValues></_>
    <_>
      <internalNodes>
        0 -1 146657 -1.1954030487686396e-03</internalNodes>
      <leafValues>
        2.6927006244659424e-01 -3.1873941421508789e-01</leafValues></_>
    <_>
      <internalNodes>
        0 -1 136847 1.6587210120633245e-03</internalNodes>
      <leafValues>
        2.5510346889495850e-01 -3.4088894724845886e-01</leafValues></_></weakClassifiers></stage13>
</opencv_storage>
