<?xml version="1.0"?>
<opencv_storage>
<stage0>
  <maxWeakCount>5</maxWeakCount>
  <stageThreshold>-4.7753068804740906e-01</stageThreshold>
  <weakClassifiers>
    <_>
      <internalNodes>
        0 -1 112475 -2.4123707413673401e-01</internalNodes>
      <leafValues>
        9.3406593799591064e-01 -7.3964494466781616e-01</leafValues></_>
    <_>
      <internalNodes>
        0 -1 14286 6.6257193684577942e-02</internalNodes>
      <leafValues>
        -7.2969502210617065e-01 7.7042734622955322e-01</leafValues></_>
    <_>
      <internalNodes>
        0 -1 143677 -5.3793977946043015e-02</internalNodes>
      <leafValues>
        8.3523321151733398e-01 -5.0297176837921143e-01</leafValues></_>
    <_>
      <internalNodes>
        0 -1 135331 -6.1214432120323181e-02</internalNodes>
      <leafValues>
        6.8278676271438599e-01 -5.6841188669204712e-01</leafValues></_>
    <_>
      <internalNodes>
        0 -1 4210 7.2476454079151154e-03</internalNodes>
      <leafValues>
        -6.8812805414199829e-01 5.8540695905685425e-01</leafValues></_></weakClassifiers></stage0>
</opencv_storage>
