<?xml version="1.0"?>
<opencv_storage>
<stage5>
  <maxWeakCount>22</maxWeakCount>
  <stageThreshold>-4.5425808429718018e-01</stageThreshold>
  <weakClassifiers>
    <_>
      <internalNodes>
        0 -1 148291 1.0577260400168598e-04</internalNodes>
      <leafValues>
        1.4705882407724857e-02 -6.4044946432113647e-01</leafValues></_>
    <_>
      <internalNodes>
        0 -1 123273 -1.0208826512098312e-01</internalNodes>
      <leafValues>
        3.9628285169601440e-01 -2.7822199463844299e-01</leafValues></_>
    <_>
      <internalNodes>
        0 -1 106745 4.5593877439387143e-04</internalNodes>
      <leafValues>
        -1.3492472469806671e-01 5.4678010940551758e-01</leafValues></_>
    <_>
      <internalNodes>
        0 -1 3268 2.3105846717953682e-02</internalNodes>
      <leafValues>
        -2.3631802201271057e-01 3.3643880486488342e-01</leafValues></_>
    <_>
      <internalNodes>
        0 -1 97061 3.7845566868782043e-02</internalNodes>
      <leafValues>
        1.0577330738306046e-01 -7.0625740289688110e-01</leafValues></_>
    <_>
      <internalNodes>
        0 -1 149397 3.7158202758291736e-05</internalNodes>
      <leafValues>
        -2.4185264110565186e-01 3.5103645920753479e-01</leafValues></_>
    <_>
      <internalNodes>
        0 -1 159433 -5.5191339924931526e-04</internalNodes>
      <leafValues>
        7.4847871065139771e-01 -1.0299140959978104e-01</leafValues></_>
    <_>
      <internalNodes>
        0 -1 151484 -1.5258061699569225e-02</internalNodes>
      <leafValues>
        6.8826192617416382e-01 -8.8052503764629364e-02</leafValues></_>
    <_>
      <internalNodes>
        0 -1 61600 6.0396473854780197e-03</internalNodes>
      <leafValues>
        -3.9875659346580505e-01 1.8613688647747040e-01</leafValues></_>
    <_>
      <internalNodes>
        0 -1 120362 -6.5973261371254921e-04</internalNodes>
      <leafValues>
        7.7430325746536255e-01 -1.0803199559450150e-01</leafValues></_>
    <_>
      <internalNodes>
        0 -1 143920 6.6913217306137085e-03</internalNodes>
      <leafValues>
        1.5354947745800018e-01 -6.0796892642974854e-01</leafValues></_>
    <_>
      <internalNodes>
        0 -1 133742 -6.1403932049870491e-03</internalNodes>
      <leafValues>
        6.7753267288208008e-01 -1.4479602873325348e-01</leafValues></_>
    <_>
      <internalNodes>
        0 -1 152051 6.3062051776796579e-04</internalNodes>
      <leafValues>
        -2.1713317930698395e-01 3.5372117161750793e-01</leafValues></_>
    <_>
      <internalNodes>
        0 -1 76772 1.0296863317489624e-01</internalNodes>
      <leafValues>
        1.1149721592664719e-01 -8.2131546735763550e-01</leafValues></_>
    <_>
      <internalNodes>
        0 -1 151784 -9.6791528631001711e-04</internalNodes>
      <leafValues>
        8.5168713331222534e-01 -1.3243333995342255e-01</leafValues></_>
    <_>
      <internalNodes>
        0 -1 161972 4.8761488869786263e-04</internalNodes>
      <leafValues>
        1.9047673046588898e-01 -4.8381957411766052e-01</leafValues></_>
    <_>
      <internalNodes>
        0 -1 125804 2.9066835995763540e-03</internalNodes>
      <leafValues>
        1.4490804076194763e-01 -5.0488865375518799e-01</leafValues></_>
    <_>
      <internalNodes>
        0 -1 1331 -1.3824366964399815e-02</internalNodes>
      <leafValues>
        -1.5772561728954315e-01 5.4237842559814453e-01</leafValues></_>
    <_>
      <internalNodes>
        0 -1 102504 6.5677682869136333e-04</internalNodes>
      <leafValues>
        -2.3088832199573517e-01 3.8045838475227356e-01</leafValues></_>
    <_>
      <internalNodes>
        0 -1 102205 1.8853838264476508e-04</internalNodes>
      <leafValues>
        -2.0732280611991882e-01 4.3524894118309021e-01</leafValues></_>
    <_>
      <internalNodes>
        0 -1 147759 -2.9488867148756981e-03</internalNodes>
      <leafValues>
        -4.8549649119377136e-01 2.0036937296390533e-01</leafValues></_>
    <_>
      <internalNodes>
        0 -1 126915 -7.1600181981921196e-03</internalNodes>
      <leafValues>
        -5.7227623462677002e-01 1.3826514780521393e-01</leafValues></_></weakClassifiers></stage5>
</opencv_storage>
