<?xml version="1.0"?>
<opencv_storage>
<stage11>
  <maxWeakCount>16</maxWeakCount>
  <stageThreshold>-5.1832777261734009e-01</stageThreshold>
  <weakClassifiers>
    <_>
      <internalNodes>
        0 -1 52231 -1.9995372742414474e-02</internalNodes>
      <leafValues>
        5.7894736528396606e-01 -3.6507937312126160e-01</leafValues></_>
    <_>
      <internalNodes>
        0 -1 50168 2.4602410197257996e-01</internalNodes>
      <leafValues>
        1.0214168578386307e-01 -1.</leafValues></_>
    <_>
      <internalNodes>
        0 -1 132769 3.3149805385619402e-03</internalNodes>
      <leafValues>
        -1.2072171270847321e-01 7.6050591468811035e-01</leafValues></_>
    <_>
      <internalNodes>
        0 -1 13417 4.8986654728651047e-03</internalNodes>
      <leafValues>
        1.0908836871385574e-01 -9.4026482105255127e-01</leafValues></_>
    <_>
      <internalNodes>
        0 -1 95727 2.3689121007919312e-03</internalNodes>
      <leafValues>
        -1.6439752280712128e-01 6.8512302637100220e-01</leafValues></_>
    <_>
      <internalNodes>
        0 -1 161891 -3.4422799944877625e-04</internalNodes>
      <leafValues>
        4.0527096390724182e-01 -2.8665205836296082e-01</leafValues></_>
    <_>
      <internalNodes>
        0 -1 157103 -5.8499845908954740e-04</internalNodes>
      <leafValues>
        6.4694184064865112e-01 -1.6619214415550232e-01</leafValues></_>
    <_>
      <internalNodes>
        0 -1 99493 1.0298222303390503e-02</internalNodes>
      <leafValues>
        -1.7292778193950653e-01 5.6474149227142334e-01</leafValues></_>
    <_>
      <internalNodes>
        0 -1 151988 4.5101642608642578e-03</internalNodes>
      <leafValues>
        -1.4178827404975891e-01 7.7954447269439697e-01</leafValues></_>
    <_>
      <internalNodes>
        0 -1 147451 -1.3767445459961891e-02</internalNodes>
      <leafValues>
        7.1158033609390259e-01 -9.6283107995986938e-02</leafValues></_>
    <_>
      <internalNodes>
        0 -1 106679 1.7350296548102051e-04</internalNodes>
      <leafValues>
        -2.0912542939186096e-01 5.3686648607254028e-01</leafValues></_>
    <_>
      <internalNodes>
        0 -1 57648 -6.1904927715659142e-03</internalNodes>
      <leafValues>
        8.0170142650604248e-01 -1.3689543306827545e-01</leafValues></_>
    <_>
      <internalNodes>
        0 -1 72462 -2.6140044792555273e-04</internalNodes>
      <leafValues>
        4.1901168227195740e-01 -2.5290602445602417e-01</leafValues></_>
    <_>
      <internalNodes>
        0 -1 49043 2.0889582112431526e-02</internalNodes>
      <leafValues>
        -2.2225622832775116e-01 4.4567140936851501e-01</leafValues></_>
    <_>
      <internalNodes>
        0 -1 37233 -5.5691022425889969e-03</internalNodes>
      <leafValues>
        6.9740253686904907e-01 -1.2936434149742126e-01</leafValues></_>
    <_>
      <internalNodes>
        0 -1 148274 -9.8038045689463615e-04</internalNodes>
      <leafValues>
        -6.4347887039184570e-01 2.1758344769477844e-01</leafValues></_></weakClassifiers></stage11>
</opencv_storage>
