<?xml version="1.0"?>
<opencv_storage>
<stage3>
  <maxWeakCount>16</maxWeakCount>
  <stageThreshold>-6.5682369470596313e-01</stageThreshold>
  <weakClassifiers>
    <_>
      <internalNodes>
        0 -1 26855 2.2590431035496294e-04</internalNodes>
      <leafValues>
        -6.3888889551162720e-01 1.1827956885099411e-01</leafValues></_>
    <_>
      <internalNodes>
        0 -1 132180 -1.5667504072189331e-01</internalNodes>
      <leafValues>
        3.9495399594306946e-01 -3.7171152234077454e-01</leafValues></_>
    <_>
      <internalNodes>
        0 -1 70892 1.2139891623519361e-05</internalNodes>
      <leafValues>
        -6.4322084188461304e-01 2.3150657117366791e-01</leafValues></_>
    <_>
      <internalNodes>
        0 -1 37783 -3.4202739596366882e-02</internalNodes>
      <leafValues>
        6.0988241434097290e-01 -2.2257094085216522e-01</leafValues></_>
    <_>
      <internalNodes>
        0 -1 117502 -3.1495713628828526e-03</internalNodes>
      <leafValues>
        -6.5115952491760254e-01 2.2934801876544952e-01</leafValues></_>
    <_>
      <internalNodes>
        0 -1 121064 -2.2464208304882050e-03</internalNodes>
      <leafValues>
        -5.0374478101730347e-01 2.8052601218223572e-01</leafValues></_>
    <_>
      <internalNodes>
        0 -1 137550 -2.1759975701570511e-02</internalNodes>
      <leafValues>
        2.6503390073776245e-01 -4.6569043397903442e-01</leafValues></_>
    <_>
      <internalNodes>
        0 -1 33271 -1.7924358835443854e-03</internalNodes>
      <leafValues>
        -5.6840419769287109e-01 2.3030298948287964e-01</leafValues></_>
    <_>
      <internalNodes>
        0 -1 139791 -3.6212797276675701e-03</internalNodes>
      <leafValues>
        -5.6127411127090454e-01 2.1724221110343933e-01</leafValues></_>
    <_>
      <internalNodes>
        0 -1 60682 -1.1306834639981389e-03</internalNodes>
      <leafValues>
        -6.7022258043289185e-01 1.5228910744190216e-01</leafValues></_>
    <_>
      <internalNodes>
        0 -1 89261 2.5237849913537502e-03</internalNodes>
      <leafValues>
        1.9877971708774567e-01 -6.9312185049057007e-01</leafValues></_>
    <_>
      <internalNodes>
        0 -1 160769 -1.0685468092560768e-02</internalNodes>
      <leafValues>
        1.6671353578567505e-01 -7.1985900402069092e-01</leafValues></_>
    <_>
      <internalNodes>
        0 -1 142450 6.3100573606789112e-03</internalNodes>
      <leafValues>
        1.4773432910442352e-01 -8.1750434637069702e-01</leafValues></_>
    <_>
      <internalNodes>
        0 -1 151914 -4.1597238741815090e-03</internalNodes>
      <leafValues>
        -7.4184238910675049e-01 1.7525789141654968e-01</leafValues></_>
    <_>
      <internalNodes>
        0 -1 161446 -2.0298932213336229e-03</internalNodes>
      <leafValues>
        3.4236416220664978e-01 -3.9199924468994141e-01</leafValues></_>
    <_>
      <internalNodes>
        0 -1 139458 -2.6220358908176422e-02</internalNodes>
      <leafValues>
        3.8675561547279358e-01 -3.6056143045425415e-01</leafValues></_></weakClassifiers></stage3>
</opencv_storage>
